LineChatCounter/LineChatCounter.py
LineChatCounter/__init__.py
LineCounter/LineCounter.py
LineCounter/__init__.py
LineChatCounter-0.0.1.dist-info/LICENSE
LineChatCounter-0.0.1.dist-info/METADATA
LineChatCounter-0.0.1.dist-info/WHEEL
LineChatCounter-0.0.1.dist-info/top_level.txt
LineChatCounter-0.0.1.dist-info/RECORD
