Metadata-Version: 2.1
Name: LineChatCounter
Version: 0.0.1
Summary: Easy to process chat text file of LINE.
Home-page: https://github.com/oxygen-TW
Author: oxygen-TW
Author-email: info@oxygentw.net
License: MIT
Platform: UNKNOWN
